{"1b36ab29eebd9dd1a50047f32bd45687":{"statistic":{"failed":0,"broken":0,"skipped":0,"passed":1,"unknown":0,"total":1},"items":[{"uid":"5bce4f4f40522c23","reportUrl":"https://EvgeniiaLV.github.io/qa_guru_26_allure/6//#testresult/5bce4f4f40522c23","status":"passed","time":{"start":1713047627005,"stop":1713047632722,"duration":5717}}]},"cef2717356e201c9394241ebba2701c8":{"statistic":{"failed":0,"broken":0,"skipped":0,"passed":1,"unknown":0,"total":1},"items":[{"uid":"ffa8a4e0b61ee85","reportUrl":"https://EvgeniiaLV.github.io/qa_guru_26_allure/6//#testresult/ffa8a4e0b61ee85","status":"passed","time":{"start":1713047635727,"stop":1713047638465,"duration":2738}}]},"92ffa6c48f91aaf50e64462ab7344543":{"statistic":{"failed":0,"broken":0,"skipped":0,"passed":1,"unknown":0,"total":1},"items":[{"uid":"8b35a2c4c6475442","reportUrl":"https://EvgeniiaLV.github.io/qa_guru_26_allure/6//#testresult/8b35a2c4c6475442","status":"passed","time":{"start":1713047632852,"stop":1713047635720,"duration":2868}}]}}